{
    "Highbridge": 219741,
    "Clason Point": 439582,
    "Eastchester": 545861,
    "Kingsbridge": 291734,
    "Woodlawn": 548957,
    "University Heights": 439582,
    "Allerton": 439582,
    "Concourse Village": 304945,
    "Concourse": 304945,
    "Wakefield": 570875,
    "Spuyten Duyvil": 439582,
    "Mott Haven": 632417,
    "Longwood": 382632,
    "Morris Heights": 542792,
    "Port Morris": 734336,
    "Fieldston": 439582,
    "Mount Eden": 439582,
    "City Island": 624524,
    "Williamsbridge": 564747,
    "Soundview": 486035,
    "Co-op City": 734336,
    "Parkchester": 205543,
    "North Riverdale": 439582,
    "Bronxdale": 439582,
    "Riverdale": 362119,
    "Norwood": 366919,
    "Claremont Village": 439582,
    "Fordham": 364256,
    "Mount Hope": 250944,
    "Van Nest": 614551,
    "Morris Park": 677849,
    "Tremont": 414012,
    "East Morrisania": 439582,
    "Hunts Point": 439582,
    "Pelham Bay": 574958,
    "Throgs Neck": 605452,
    "West Farms": 439582,
    "Morrisania": 439582,
    "Pelham Gardens": 677247,
    "Belmont": 470459,
    "Baychester": 641272,
    "Melrose": 363543,
    "Schuylerville": 270201,
    "Castle Hill": 598727,
    "Olinville": 439582,
    "Edenwald": 439582,
    "Westchester Square": 439582,
    "Unionport": 439582
}